python_atom_sdk/__init__.py
python_atom_sdk/api.py
python_atom_sdk-0.3.dist-info/METADATA
python_atom_sdk-0.3.dist-info/WHEEL
python_atom_sdk-0.3.dist-info/top_level.txt
python_atom_sdk-0.3.dist-info/RECORD
