Metadata-Version: 2.1
Name: python-atom-sdk
Version: 0.3
Summary: python_atom_sdk
Home-page: https://github.com/MemoryD/mxgames
Author: duenldnkjdhlkq
Author-email: duenldnkjdhlkq@foxmail.com
License: MIT
Platform: UNKNOWN
Classifier: Programming Language :: Python
Classifier: Programming Language :: Python :: 3
Classifier: Programming Language :: Python :: 3.5
Classifier: Programming Language :: Python :: 3.5
Classifier: Programming Language :: Python :: 3.6
Classifier: Programming Language :: Python :: 3.7
